neuropot/__init__.py
neuropot/preprocessing/__init__.py
neuropot/preprocessing/acpc_correction.py
neuropot/preprocessing/intensity_normalization.py
neuropot/preprocessing/normalization.py
neuropot/preprocessing/segmentation.py
neuropot/preprocessing/skull_stripping.py
neuropot/preprocessing/smoothing.py
neuropot/preprocessing/template/mni152.nii
neuropot/preprocessing/template/template.nii
neuropot/preprocessing/template/vbm_template.nii
neuropot-0.1.9.data/scripts/ACPCAlignment.sh
neuropot-0.1.9.dist-info/METADATA
neuropot-0.1.9.dist-info/WHEEL
neuropot-0.1.9.dist-info/top_level.txt
neuropot-0.1.9.dist-info/RECORD
